Workbook

Sheet Input 
A1: LOAN & EMI CALCULATOR
A3: Loan Amount (₹/$) | B3: 500000
A4: Annual Interest Rate (%) | B4: 8.5
A5: Loan Tenure (Months) | B5: 60

Sheet EMI_Calculation
A1: EMI CALCULATION
A3: Loan Amount | B3: ='Input '!B3 -> 500000
A4: Monthly Interest Rate | B4: ='Input '!B4/12/100 -> 0.0070833333
A5: Number of Payments | B5: ='Input '!B5 -> 60
A6: Monthly EMI | B6: =-PMT(B4,B5,B3) -> 10258.266

Sheet Amortization_Schedule
A1: MONTH | B1: OPENING BALANCE | C1: EMI | D1: INTEREST PAID | E1: PRINCIPAL PAID | F1: CLOSING BALANCE | H1: LOAN SUMMARY
A2: 1 | B2: =EMI_Calculation!B3 -> 500000 | C2: =EMI_Calculation!B6 -> 10258.266 | D2: =B2*EMI_Calculation!B4 -> 3541.6667 | E2: =C2-D2 -> 6716.599 | F2: =B2-E2 -> 493283.4
A3: =A2+1 -> 2 | B3: =F2 -> 493283.4 | C3: =C2 -> 10258.266 | D3: =B3*EMI_Calculation!$B$4 -> 3494.0908 | E3: =C3-D3 -> 6764.1749 | F3: =B3-E3 -> 486519.23 | H3: Total Amount Paid | I3: =C2*60 -> 615495.94
A4: =A3+1 -> 3 | B4: =F3 -> 486519.23 | C4: =C3 -> 10258.266 | D4: =B4*EMI_Calculation!$B$4 -> 3446.1779 | E4: =C4-D4 -> 6812.0878 | F4: =B4-E4 -> 479707.14 | H4: Total Interest Paid | I4: =SUM(D2:D61) -> 115495.94
A5: =A4+1 -> 4 | B5: =F4 -> 479707.14 | C5: =C4 -> 10258.266 | D5: =B5*EMI_Calculation!$B$4 -> 3397.9256 | E5: =C5-D5 -> 6860.3401 | F5: =B5-E5 -> 472846.8 | H5: Total Principal Paid | I5: =SUM(E2:E61) -> 500000
A6: =A5+1 -> 5 | B6: =F5 -> 472846.8 | C6: =C5 -> 10258.266 | D6: =B6*EMI_Calculation!$B$4 -> 3349.3315 | E6: =C6-D6 -> 6908.9342 | F6: =B6-E6 -> 465937.86
A7: =A6+1 -> 6 | B7: =F6 -> 465937.86 | C7: =C6 -> 10258.266 | D7: =B7*EMI_Calculation!$B$4 -> 3300.3932 | E7: =C7-D7 -> 6957.8725 | F7: =B7-E7 -> 458979.99
A8: =A7+1 -> 7 | B8: =F7 -> 458979.99 | C8: =C7 -> 10258.266 | D8: =B8*EMI_Calculation!$B$4 -> 3251.1083 | E8: =C8-D8 -> 7007.1574 | F8: =B8-E8 -> 451972.83
A9: =A8+1 -> 8 | B9: =F8 -> 451972.83 | C9: =C8 -> 10258.266 | D9: =B9*EMI_Calculation!$B$4 -> 3201.4742 | E9: =C9-D9 -> 7056.7914 | F9: =B9-E9 -> 444916.04
A10: =A9+1 -> 9 | B10: =F9 -> 444916.04 | C10: =C9 -> 10258.266 | D10: =B10*EMI_Calculation!$B$4 -> 3151.4886 | E10: =C10-D10 -> 7106.777 | F10: =B10-E10 -> 437809.27
A11: =A10+1 -> 10 | B11: =F10 -> 437809.27 | C11: =C10 -> 10258.266 | D11: =B11*EMI_Calculation!$B$4 -> 3101.149 | E11: =C11-D11 -> 7157.1167 | F11: =B11-E11 -> 430652.15
A12: =A11+1 -> 11 | B12: =F11 -> 430652.15 | C12: =C11 -> 10258.266 | D12: =B12*EMI_Calculation!$B$4 -> 3050.4527 | E12: =C12-D12 -> 7207.8129 | F12: =B12-E12 -> 423444.34
A13: =A12+1 -> 12 | B13: =F12 -> 423444.34 | C13: =C12 -> 10258.266 | D13: =B13*EMI_Calculation!$B$4 -> 2999.3974 | E13: =C13-D13 -> 7258.8683 | F13: =B13-E13 -> 416185.47
A14: =A13+1 -> 13 | B14: =F13 -> 416185.47 | C14: =C13 -> 10258.266 | D14: =B14*EMI_Calculation!$B$4 -> 2947.9804 | E14: =C14-D14 -> 7310.2853 | F14: =B14-E14 -> 408875.18
A15: =A14+1 -> 14 | B15: =F14 -> 408875.18 | C15: =C14 -> 10258.266 | D15: =B15*EMI_Calculation!$B$4 -> 2896.1992 | E15: =C15-D15 -> 7362.0665 | F15: =B15-E15 -> 401513.12
A16: =A15+1 -> 15 | B16: =F15 -> 401513.12 | C16: =C15 -> 10258.266 | D16: =B16*EMI_Calculation!$B$4 -> 2844.0512 | E16: =C16-D16 -> 7414.2144 | F16: =B16-E16 -> 394098.9
A17: =A16+1 -> 16 | B17: =F16 -> 394098.9 | C17: =C16 -> 10258.266 | D17: =B17*EMI_Calculation!$B$4 -> 2791.5339 | E17: =C17-D17 -> 7466.7318 | F17: =B17-E17 -> 386632.17
... A61: =A60+1 -> 60 | B61: =F60 -> 10186.114 | C61: =C60 -> 10258.266 | D61: =B61*EMI_Calculation!$B$4 -> 72.151641 | E61: =C61-D61 -> 10186.114 | F61: =B61-E61 -> 9.4587449e-11

Sheet Loan_Comparison
A1: USER_ID | B1: AGE | C1: GENDER | D1: EDUCATION_LEVEL | E1: EMPLOYMENT_STATUS | F1: JOB_TITAL | G1: MONTHLY_INCOME_USD | H1: MONTHLY_EXPENSES_USD | I1: SAVINGS_USD | J1: HAS_LOAN | K1: LOAN_TYPE | L1: LOAN_AMOUNT_USD | M1: LOAN_TERM_MONTHS | N1: MONTHLY_EMI_USD | O1: LOAN_INTEREST_RATE_PCT | P1: DEBT_TO_INCOME_RATIO | Q1: CREDIT_SCORE | R1: SAVINGS_TO_INCOME_RATIO | S1: REGION | T1: RECORD_DATE | V1: LOAN OPTION | W1: LOAN AMOUNT | X1: INTEREST RATE (%) | Y1: TENURE (MONTHS) | Z1: MONTHLY EMI | AA1: TOTAL PAYMENT | AB1: TOTAL INTEREST
A2: U00002 | B2: 19 | C2: Female | D2: PhD | E2: Employed | F2: Salesperson | G2: 3531.73 | H2: 2367.99 | I2: 260869.1 | J2: Yes | K2: Education | L2: 146323.34 | M2: 36 | N2: 4953.5 | O2: 13.33 | P2: 1.4 | Q2: 543 | R2: 6.16 | S2: North America | T2: 44605 | V2: Option A | W2: 500000 | X2: 8.5 | Y2: 60 | Z2: =-PMT(X2/12/100,Y2,W2) -> 10258.266 | AA2: =Z2*Y2 -> 615495.94 | AB2: =AA2-W2 -> 115495.94
A3: U00004 | B3: 25 | C3: Male | D3: PhD | E3: Employed | F3: Manager | G3: 5894.88 | H3: 4440.12 | I3: 304815.51 | J3: Yes | K3: Business | L3: 93242.37 | M3: 24 | N3: 4926.57 | O3: 23.93 | P3: 0.84 | Q3: 461 | R3: 4.31 | S3: Europe | T3: 45201 | V3: Option B | W3: 500000 | X3: 10 | Y3: 48 | Z3: =-PMT(X3/12/100,Y3,W3) -> 12681.292 | AA3: =Z3*Y3 -> 608702 | AB3: =AA3-W3 -> 108702
A4: U00006 | B4: 62 | C4: Male | D4: Master | E4: Employed | F4: Student | G4: 4051 | H4: 2244.42 | I4: 194901.41 | J4: Yes | K4: Car | L4: 407915.25 | M4: 12 | N4: 38219.81 | O4: 22.21 | P4: 9.43 | Q4: 718 | R4: 4.01 | S4: North America | T4: 45700 | V4: Option C | W4: 500000 | X4: 7.5 | Y4: 72 | Z4: =-PMT(X4/12/100,Y4,W4) -> 8645.0561 | AA4: =Z4*Y4 -> 622444.04 | AB4: =AA4-W4 -> 122444.04
A5: U00007 | B5: 22 | C5: Female | D5: Master | E5: Student | F5: Accountant | G5: 983.69 | H5: 332.62 | I5: 37522.56 | J5: Yes | K5: Car | L5: 296057.6 | M5: 180 | N5: 6773.29 | O5: 26.95 | P5: 6.89 | Q5: 761 | R5: 3.18 | S5: Asia | T5: 45444 | Z5: =-PMT(X5/12/100,Y5,W5) -> #NUM! | AA5: =Z5*Y5 -> #NUM! | AB5: =AA5-W5 -> #NUM!
A6: U00010 | B6: 61 | C6: Male | D6: Master | E6: Employed | F6: Student | G6: 5216.18 | H6: 4369.36 | I6: 203320.5 | J6: Yes | K6: Education | L6: 324197.37 | M6: 360 | N6: 6782.37 | O6: 25.09 | P6: 1.3 | Q6: 558 | R6: 3.25 | S6: Asia | T6: 45619 | Z6: =-PMT(X6/12/100,Y6,W6) -> #NUM! | AA6: =Z6*Y6 -> #NUM! | AB6: =AA6-W6 -> #NUM!
A7: U00011 | B7: 26 | C7: Female | D7: Master | E7: Employed | F7: Manager | G7: 3677.43 | H7: 2247.92 | I7: 311546.91 | J7: Yes | K7: Education | L7: 127703.79 | M7: 240 | N7: 1818.01 | O7: 16.43 | P7: 0.49 | Q7: 412 | R7: 7.06 | S7: Other | T7: 44806 | Z7: =-PMT(X7/12/100,Y7,W7) -> #NUM! | AA7: =Z7*Y7 -> #NUM! | AB7: =AA7-W7 -> #NUM!
A8: U00014 | B8: 65 | C8: Female | D8: High School | E8: Employed | F8: Driver | G8: 5546.28 | H8: 3630.24 | I8: 453101.38 | J8: Yes | K8: Car | L8: 404941.02 | M8: 60 | N8: 10823.31 | O8: 20.42 | P8: 1.95 | Q8: 788 | R8: 6.81 | S8: North America | T8: 44576
A9: U00021 | B9: 23 | C9: Male | D9: High School | E9: Student | F9: Engineer | G9: 8237.77 | H9: 7316.78 | I9: 83622.72 | J9: Yes | K9: Business | L9: 425717.2 | M9: 36 | N9: 13258.1 | O9: 7.58 | P9: 1.61 | Q9: 622 | R9: 0.85 | S9: Europe | T9: 45009
A10: U00022 | B10: 49 | C10: Female | D10: Bachelor | E10: Employed | F10: Teacher | G10: 7093.07 | H10: 3500.65 | I10: 723648.99 | J10: Yes | K10: Home | L10: 180386.08 | M10: 240 | N10: 2286.5 | O10: 14.33 | P10: 0.32 | Q10: 707 | R10: 8.5 | S10: Other | T10: 44999
A11: U00023 | B11: 24 | C11: Female | D11: Master | E11: Self-employed | F11: Driver | G11: 1694.87 | H11: 604.03 | I11: 118470.87 | J11: Yes | K11: Education | L11: 78365.77 | M11: 180 | N11: 1315.94 | O11: 18.95 | P11: 0.78 | Q11: 641 | R11: 5.82 | S11: North America | T11: 45255
A12: U00024 | B12: 69 | C12: Male | D12: Bachelor | E12: Employed | F12: Salesperson | G12: 998.46 | H12: 612.4 | I12: 92532.51 | J12: Yes | K12: Education | L12: 229175.32 | M12: 180 | N12: 1741.49 | O12: 4.4 | P12: 1.74 | Q12: 649 | R12: 7.72 | S12: Asia | T12: 44703
A13: U00025 | B13: 57 | C13: Female | D13: Other | E13: Employed | F13: Driver | G13: 2676.43 | H13: 1507.85 | I13: 28157.7 | J13: Yes | K13: Education | L13: 41355.61 | M13: 360 | N13: 745.27 | O13: 21.59 | P13: 0.28 | Q13: 357 | R13: 0.88 | S13: Europe | T13: 44541
A14: U00030 | B14: 18 | C14: Other | D14: PhD | E14: Employed | F14: Teacher | G14: 6561.08 | H14: 2121.71 | I14: 489775.18 | J14: Yes | K14: Home | L14: 160168.84 | M14: 24 | N14: 7393.94 | O14: 10.04 | P14: 1.13 | Q14: 495 | R14: 6.22 | S14: Europe | T14: 44894
A15: U00034 | B15: 22 | C15: Male | D15: Bachelor | E15: Self-employed | F15: Doctor | G15: 5968.05 | H15: 5178.58 | I15: 561103.95 | J15: Yes | K15: Education | L15: 247715.73 | M15: 240 | N15: 6187.05 | O15: 29.89 | P15: 1.04 | Q15: 432 | R15: 7.83 | S15: Asia | T15: 45405
A16: U00036 | B16: 67 | C16: Female | D16: High School | E16: Employed | F16: Unemployed | G16: 6715.76 | H16: 5990.35 | I16: 306664.24 | J16: Yes | K16: Business | L16: 119105.91 | M16: 240 | N16: 2948.4 | O16: 29.62 | P16: 0.44 | Q16: 431 | R16: 3.81 | S16: Africa | T16: 45760
A17: U00037 | B17: 23 | C17: Female | D17: Bachelor | E17: Employed | F17: Student | G17: 5715.32 | H17: 2095.91 | I17: 341340.99 | J17: Yes | K17: Business | L17: 286165.04 | M17: 60 | N17: 5560.36 | O17: 6.21 | P17: 0.97 | Q17: 660 | R17: 4.98 | S17: North America | T17: 45288
A18: U00039 | B18: 62 | C18: Other | D18: High School | E18: Unemployed | F18: Unemployed | G18: 5687.15 | H18: 1963.55 | I18: 119125.28 | J18: Yes | K18: Car | L18: 227815.99 | M18: 120 | N18: 4681 | O18: 21.82 | P18: 0.82 | Q18: 558 | R18: 1.75 | S18: North America | T18: 45034
A19: U00040 | B19: 28 | C19: Male | D19: Other | E19: Unemployed | F19: Manager | G19: 1867.36 | H19: 1255.01 | I19: 63775.73 | J19: Yes | K19: Home | L19: 194745.92 | M19: 24 | N19: 9002.72 | O19: 10.18 | P19: 4.82 | Q19: 340 | R19: 2.85 | S19: Africa | T19: 44607
... A12996: U32421 | B12996: 51 | C12996: Female | D12996: Master | E12996: Employed | F12996: Student | G12996: 5725.78 | H12996: 4965.02 | I12996: 17247.57 | J12996: Yes | K12996: Home | L12996: 83602.57 | M12996: 12 | N12996: 7605.13 | O12996: 16.5 | P12996: 1.33 | Q12996: 453 | R12996: 0.25 | S12996: North America | T12996: 45814

Sheet Dashboard
A1: LOAN & EMI DASHHBOARD
A3: LOAN AMOUNT | B3: ='Input '!B3 -> 500000 | D3: Principal | E3: =Amortization_Schedule!I5 -> 500000
A4: Interest Rate | B4: ='Input '!B4 -> 8.5 | D4: Interest | E4: =Amortization_Schedule!I4 -> 115495.94
A5: Tenure (Months) | B5: ='Input '!B5 -> 60
A6: Monthly EMI | B6: =EMI_Calculation!B6 -> 10258.266
A7: Total Interest Paid | B7: =Amortization_Schedule!I4 -> 115495.94
A8: Total Amount Paid | B8: =Amortization_Schedule!I3 -> 615495.94
